{ "tickets": {
    "overall": {
      "direct": {
        "active": 6,
        "inactive": 0
      },
      "referrals": {
        "active": 3,
        "inactive": 33
      },
      "bonuses": {
        "active": 0,
        "inactive": 0
      }
    },
    "direct": {
      "ticketsForRegistration": {
        "active": 1,
        "inactive": 0
      },
      "usd": {
        "balance": 250,
        "active": 5,
        "inactive": 0
      },
      "emrx": {
        "balance": 0,
        "active": 0,
        "inactive": 0
      }
    },
    "referrals": [
      {
        "tickets": 2,
        "email": "iogancombatiente+388@gmail.com",
        "isActive": 1,
        "subreferrals": 2,
        "activeSubreferrals": 1
      },
      {
        "tickets": 2,
        "email": "iogancombatiente+777@gmail.com",
        "isActive": 0,
        "subreferrals": 2,
        "activeSubreferrals": 0
      },
      {
        "tickets": 2,
        "email": "inna.lisovskaya100+ivan1@gmail.com",
        "isActive": 0,
        "subreferrals": 0,
        "activeSubreferrals": 0
      },
      {
        "tickets": 2,
        "email": "inna.lisovskaya100+ivan2@gmail.com",
        "isActive": 0,
        "subreferrals": 0,
        "activeSubreferrals": 0
      },
      {
        "tickets": 2,
        "email": "inna.lisovskaya100+ivan3@gmail.com",
        "isActive": 0,
        "subreferrals": 0,
        "activeSubreferrals": 0
      },
      {
        "tickets": 2,
        "email": "inna.lisovskaya100+ivan4@gmail.com",
        "isActive": 0,
        "subreferrals": 0,
        "activeSubreferrals": 0
      },
      {
        "tickets": 2,
        "email": "inna.lisovskaya100+ivan5@gmail.com",
        "isActive": 0,
        "subreferrals": 0,
        "activeSubreferrals": 0
      },
      {
        "tickets": 2,
        "email": "inna.lisovskaya100+ivan6@gmail.com",
        "isActive": 0,
        "subreferrals": 0,
        "activeSubreferrals": 0
      },
      {
        "tickets": 2,
        "email": "inna.lisovskaya100+ivan7@gmail.com",
        "isActive": 0,
        "subreferrals": 0,
        "activeSubreferrals": 0
      },
      {
        "tickets": 2,
        "email": "inna.lisovskaya100+ivan8@gmail.com",
        "isActive": 0,
        "subreferrals": 0,
        "activeSubreferrals": 0
      },
      {
        "tickets": 2,
        "email": "inna.lisovskaya100+ivan5@gmail.com",
        "isActive": 0,
        "subreferrals": 0,
        "activeSubreferrals": 0
      },
      {
        "tickets": 3,
        "email": "inna.lisovskaya100+ivan6@gmail.com",
        "isActive": 0,
        "subreferrals": 0,
        "activeSubreferrals": 0
      },
      {
        "tickets": 11,
        "email": "inna.lisovskaya100+ivan7@gmail.com",
        "isActive": 0,
        "subreferrals": 0,
        "activeSubreferrals": 0
      },
      {
        "tickets": 5,
        "email": "inna.lisovskaya100+ivan8@gmail.com",
        "isActive": 0,
        "subreferrals": 0,
        "activeSubreferrals": 0
      },
      {
        "tickets": 2,
        "email": "iogancombatiente+388@gmail.com",
        "isActive": 1,
        "subreferrals": 2,
        "activeSubreferrals": 1
      },
      {
        "tickets": 2,
        "email": "iogancombatiente+777@gmail.com",
        "isActive": 0,
        "subreferrals": 2,
        "activeSubreferrals": 0
      },
      {
        "tickets": 2,
        "email": "inna.lisovskaya100+ivan1@gmail.com",
        "isActive": 0,
        "subreferrals": 0,
        "activeSubreferrals": 0
      },
      {
        "tickets": 2,
        "email": "inna.lisovskaya100+ivan2@gmail.com",
        "isActive": 0,
        "subreferrals": 0,
        "activeSubreferrals": 0
      },
      {
        "tickets": 2,
        "email": "inna.lisovskaya100+ivan3@gmail.com",
        "isActive": 0,
        "subreferrals": 0,
        "activeSubreferrals": 0
      },
      {
        "tickets": 2,
        "email": "inna.lisovskaya100+ivan4@gmail.com",
        "isActive": 0,
        "subreferrals": 0,
        "activeSubreferrals": 0
      }  
     
    ],
    "bonuses": []
  }
  }